ewatercycle_leakybucket/__init__.py
ewatercycle_leakybucket/model.py
ewatercycle_leakybucket-0.0.2.dist-info/METADATA
ewatercycle_leakybucket-0.0.2.dist-info/WHEEL
ewatercycle_leakybucket-0.0.2.dist-info/entry_points.txt
ewatercycle_leakybucket-0.0.2.dist-info/licenses/LICENSE.txt
ewatercycle_leakybucket-0.0.2.dist-info/RECORD
