Metadata-Version: 2.3
Name: ewatercycle-leakybucket
Version: 0.0.2
Summary: Template project for starting a new eWaterCycle plugin
Author-email: "Bart Schilperoort, Peter Kalverla, Stefan Verhoeven" <b.schilperoort@esciencecenter.nl>
License-Expression: Apache-2.0
License-File: LICENSE.txt
Keywords: ewatercycle,hydrology
Classifier: Intended Audience :: Developers
Classifier: License :: OSI Approved :: Apache Software License
Classifier: Natural Language :: English
Classifier: Operating System :: OS Independent
Classifier: Programming Language :: Python
Classifier: Programming Language :: Python :: 3 :: Only
Requires-Dist: ewatercycle>=2.1.0
